{"3264":{"x":32,"y":64,"m":"wall","l":40},"6464":{"x":64,"y":64,"m":"wall","l":40},"9664":{"x":96,"y":64,"m":"wall","l":40},"12864":{"x":128,"y":64,"m":"wall","l":40},"16064":{"x":160,"y":64,"m":"water","l":40},"19264":{"x":192,"y":64,"m":"water","l":40},"22464":{"x":224,"y":64,"m":"water","l":40},"25664":{"x":256,"y":64,"m":"water","l":40},"28864":{"x":288,"y":64,"m":"woods","l":40},"28896":{"x":288,"y":96,"m":"woods","l":40},"32064":{"x":320,"y":64,"m":"woods","l":40},"32096":{"x":320,"y":96,"m":"woods","l":40},"32160":{"x":32,"y":160,"m":"water","l":40},"32320":{"x":32,"y":320,"m":"wall","l":40},"32416":{"x":32,"y":416,"m":"wall","l":40},"32448":{"x":32,"y":448,"m":"wall","l":40},"35264":{"x":352,"y":64,"m":"wall","l":40},"38464":{"x":384,"y":64,"m":"wall","l":40},"41664":{"x":416,"y":64,"m":"wall","l":40},"44864":{"x":448,"y":64,"m":"wall","l":40},"48064":{"x":480,"y":64,"m":"wall","l":40},"64128":{"x":64,"y":128,"m":"woods","l":40},"64160":{"x":64,"y":160,"m":"woods","l":40},"64320":{"x":64,"y":320,"m":"wall","l":40},"64416":{"x":64,"y":416,"m":"wall","l":40},"64448":{"x":64,"y":448,"m":"wall","l":40},"96128":{"x":96,"y":128,"m":"woods","l":40},"96160":{"x":96,"y":160,"m":"woods","l":40},"96416":{"x":96,"y":416,"m":"water","l":40},"128128":{"x":128,"y":128,"m":"wall","l":40},"128160":{"x":128,"y":160,"m":"wall","l":40},"128192":{"x":128,"y":192,"m":"wall","l":40},"128224":{"x":128,"y":224,"m":"wall","l":40},"128256":{"x":128,"y":256,"m":"wall","l":40},"128288":{"x":128,"y":288,"m":"wall","l":40},"128320":{"x":128,"y":320,"m":"woods","l":40},"128352":{"x":128,"y":352,"m":"woods","l":40},"128416":{"x":128,"y":416,"m":"water","l":40},"160128":{"x":160,"y":128,"m":"wall","l":40},"160160":{"x":160,"y":160,"m":"water","l":40},"160192":{"x":160,"y":192,"m":"woods","l":40},"160224":{"x":160,"y":224,"m":"water","l":40},"160256":{"x":160,"y":256,"m":"water","l":40},"160288":{"x":160,"y":288,"m":"wall","l":40},"160320":{"x":160,"y":320,"m":"woods","l":40},"160352":{"x":160,"y":352,"m":"woods","l":40},"160416":{"x":160,"y":416,"m":"water","l":40},"192128":{"x":192,"y":128,"m":"wall","l":40},"192160":{"x":192,"y":160,"m":"water","l":40},"192192":{"x":192,"y":192,"m":"woods","l":40},"192224":{"x":192,"y":224,"m":"woods","l":40},"192256":{"x":192,"y":256,"m":"water","l":40},"192288":{"x":192,"y":288,"m":"wall","l":40},"192416":{"x":192,"y":416,"m":"water","l":40},"224128":{"x":224,"y":128,"m":"wall","l":40},"224160":{"x":224,"y":160,"m":"woods","l":40},"224192":{"x":224,"y":192,"m":"woods","l":40},"224224":{"x":224,"y":224,"m":"woods","l":40},"224256":{"x":224,"y":256,"m":"woods","l":40},"224288":{"x":224,"y":288,"m":"wall","l":40},"224416":{"x":224,"y":416,"m":"woods","l":40},"256128":{"x":256,"y":128,"m":"wall","l":40},"256160":{"x":256,"y":160,"m":"water","l":40},"256192":{"x":256,"y":192,"m":"woods","l":40},"256224":{"x":256,"y":224,"m":"woods","l":40},"256256":{"x":256,"y":256,"m":"water","l":40},"256288":{"x":256,"y":288,"m":"wall","l":40},"256416":{"x":256,"y":416,"m":"woods","l":40},"288128":{"x":288,"y":128,"m":"wall","l":40},"288160":{"x":288,"y":160,"m":"water","l":40},"288192":{"x":288,"y":192,"m":"water","l":40},"288224":{"x":288,"y":224,"m":"woods","l":40},"288256":{"x":288,"y":256,"m":"water","l":40},"288288":{"x":288,"y":288,"m":"wall","l":40},"288416":{"x":288,"y":416,"m":"woods","l":40},"320128":{"x":320,"y":128,"m":"wall","l":40},"320160":{"x":320,"y":160,"m":"wall","l":40},"320192":{"x":320,"y":192,"m":"wall","l":40},"320224":{"x":320,"y":224,"m":"wall","l":40},"320256":{"x":320,"y":256,"m":"wall","l":40},"320288":{"x":320,"y":288,"m":"wall","l":40},"320320":{"x":320,"y":320,"m":"wall","l":40},"320352":{"x":320,"y":352,"m":"wall","l":40},"320384":{"x":320,"y":384,"m":"wall","l":40},"320416":{"x":320,"y":416,"m":"woods","l":40},"352256":{"x":352,"y":256,"m":"woods","l":40},"352288":{"x":352,"y":288,"m":"woods","l":40},"352416":{"x":352,"y":416,"m":"wall","l":40},"352448":{"x":352,"y":448,"m":"wall","l":40},"384256":{"x":384,"y":256,"m":"woods","l":40},"384288":{"x":384,"y":288,"m":"woods","l":40},"384416":{"x":384,"y":416,"m":"wall","l":40},"384448":{"x":384,"y":448,"m":"wall","l":40},"416288":{"x":416,"y":288,"m":"wall","l":40},"416416":{"x":416,"y":416,"m":"wall","l":40},"416448":{"x":416,"y":448,"m":"wall","l":40},"448128":{"x":448,"y":128,"m":"wall","l":40},"448160":{"x":448,"y":160,"m":"wall","l":40},"448288":{"x":448,"y":288,"m":"wall","l":40},"448416":{"x":448,"y":416,"m":"wall","l":40},"448448":{"x":448,"y":448,"m":"wall","l":40},"480128":{"x":480,"y":128,"m":"wall","l":40},"480160":{"x":480,"y":160,"m":"wall","l":40},"480288":{"x":480,"y":288,"m":"wall","l":40},"480416":{"x":480,"y":416,"m":"wall","l":40},"0416":{"x":0,"y":416,"m":"wall","l":40},"0448":{"x":0,"y":448,"m":"wall","l":40},"0320":{"x":0,"y":320,"m":"wall","l":40},"064":{"x":0,"y":64,"m":"wall","l":40},"0160":{"x":0,"y":160,"m":"water","l":40}}